LICENSE
MANIFEST.in
README.rst
setup.cfg
setup.py
tests/__init__.py
tests/test_dumping.py
tests/test_field.py
tests/test_flask_request.py
tests/test_mappings.py
tests/test_schema.py
wr_schemas/__init__.py
wr_schemas/field.py
wr_schemas/flask_request.py
wr_schemas/mappings.py
wr_schemas/schema.py
wr_schemas/utils.py
wr_schemas.egg-info/PKG-INFO
wr_schemas.egg-info/SOURCES.txt
wr_schemas.egg-info/dependency_links.txt
wr_schemas.egg-info/top_level.txt