Metadata-Version: 1.1
Name: wr-schemas
Version: 0.5.0
Summary: wr-schemas
Home-page: https://github.com/jbasko/wr-schemas
Author: Jazeps Basko
Author-email: jazeps.basko@gmail.com
License: MIT
Platform: UNKNOWN
Classifier: Development Status :: 4 - Beta
Classifier: Intended Audience :: Developers
Classifier: Programming Language :: Python
Classifier: Programming Language :: Python :: 3
Classifier: Programming Language :: Python :: 3.5
Classifier: Programming Language :: Python :: 3.6
Classifier: License :: OSI Approved :: MIT License
